README.rst
setup.py
NicePrinter.egg-info/PKG-INFO
NicePrinter.egg-info/SOURCES.txt
NicePrinter.egg-info/dependency_links.txt
NicePrinter.egg-info/top_level.txt
src/NicePrinter/__init__.py
src/NicePrinter/niceprinter.py