Metadata-Version: 1.1
Name: NicePrinter
Version: 1.0.2
Summary: A simple Python project to generate nice prints
Home-page: https://github.com/24aitor/NicePrinter
Author: Aitor Riba Archilla
Author-email: contact@aitorriba.com
License: MIT
Keywords: print shell
Platform: UNKNOWN
Classifier: Development Status :: 3 - Alpha
Classifier: Intended Audience :: Developers
Classifier: Topic :: Software Development :: Build Tools
Classifier: License :: OSI Approved :: MIT License
Classifier: Programming Language :: Python :: 3
Classifier: Programming Language :: Python :: 3.3
Classifier: Programming Language :: Python :: 3.4
Classifier: Programming Language :: Python :: 3.5
